LICENSE
MANIFEST.in
README.rst
setup.py
pokercore/__init__.py
pokercore/card.py
pokercore/deck.py
pokercore/exceptions.py
pokercore/hand.py
pokercore.egg-info/PKG-INFO
pokercore.egg-info/SOURCES.txt
pokercore.egg-info/dependency_links.txt
pokercore.egg-info/top_level.txt
pokercore/test/__init__.py
pokercore/test/test_card.py
pokercore/test/test_deck.py
pokercore/test/test_hand.py
pokercore/test/testcases