Metadata-Version: 1.1
Name: pokercore
Version: 0.1.4
Summary: A poker engine core, in Python
Home-page: https://github.com/amikrop/pokercore
Author: Aristotelis Mikropoulos
Author-email: amikrop@gmail.com
License: MIT
Platform: UNKNOWN
Classifier: Development Status :: 3 - Alpha
Classifier: Intended Audience :: Developers
Classifier: License :: OSI Approved :: MIT License
Classifier: Operating System :: OS Independent
Classifier: Programming Language :: Python
Classifier: Topic :: Games/Entertainment
